fish_speech_rs-0.3.0.dist-info/METADATA
fish_speech_rs-0.3.0.dist-info/WHEEL
fish_speech/__init__.py
fish_speech/fish_speech.cpython-310-darwin.so
fish_speech_rs-0.3.0.dist-info/RECORD
