Metadata-Version: 2.4
Name: fish_speech_rs
Version: 0.3.0
Classifier: Programming Language :: Rust
Classifier: Programming Language :: Python :: Implementation :: CPython
Classifier: Programming Language :: Python :: Implementation :: PyPy
Requires-Dist: numpy>=1.21.0
Summary: High-performance speech synthesis
Requires-Python: >=3.9
